binance_data_loader/__init__.py
binance_data_loader/downloader.py
binance_data_loader/loader.py
binance_data_loader/metadata.py
binance_data_loader/processor.py
binance_data_loader/schema.py
binance_data_loader/types.py
binance_data_loader/utils.py
binance_data_loader-0.1.2.dist-info/METADATA
binance_data_loader-0.1.2.dist-info/WHEEL
binance_data_loader-0.1.2.dist-info/RECORD
