Metadata-Version: 2.4
Name: binance-data-loader
Version: 0.1.2
Summary: A Python library for downloading and processing Binance Vision historical data
Project-URL: Homepage, https://github.com/HuakunShen/binance-data-loader
Project-URL: Repository, https://github.com/HuakunShen/binance-data-loader.git
Project-URL: Issues, https://github.com/HuakunShen/binance-data-loader/issues
Author-email: Huakun Shen <huakun.shen@huakunshen.com>
License: MIT
Keywords: binance,crypto,data,historical,klines,trading
Classifier: Development Status :: 3 - Alpha
Classifier: Intended Audience :: Developers
Classifier: Intended Audience :: Financial and Insurance Industry
Classifier: License :: OSI Approved :: MIT License
Classifier: Programming Language :: Python :: 3
Classifier: Programming Language :: Python :: 3.12
Classifier: Programming Language :: Python :: 3.13
Classifier: Topic :: Office/Business :: Financial
Classifier: Topic :: Software Development :: Libraries :: Python Modules
Requires-Python: >=3.12
Requires-Dist: pandera>=0.28.0
Requires-Dist: polars>=1.36.1
Requires-Dist: requests>=2.32.5
Requires-Dist: tqdm>=4.66.0
Requires-Dist: xmltodict>=1.0.2
